rallf/__init__.py
rallf/cli.py
rallf/args/__init__.py
rallf/args/rallf_args.py
rallf/sample/__init__.py
rallf/sample/task/__init__.py
rallf/sample/task/hello/__init__.py
rallf/sample/task/hello/hello.py
rallf/sample/task/install_app/__init__.py
rallf/sample/task/install_app/image_finder.py
rallf/sample/task/install_app/install_app.py
rallf/sample/task/title/__init__.py
rallf/sample/task/title/title.py
rallf/sample/task/twitter/__init__.py
rallf/sample/task/twitter/src/__init__.py
rallf/sample/task/twitter/src/main/__init__.py
rallf/sample/task/twitter/src/main/twitter.py
rallf/sample/task/twitter/src/main/user.py
rallf/sdk/__init__.py
rallf/sdk/listener.py
rallf/sdk/logger.py
rallf/sdk/network.py
rallf/sdk/rallf_error.py
rallf/sdk/robot.py
rallf/sdk/task.py
rallf/tools/__init__.py
rallf/tools/communicator.py
rallf/tools/execution.py
rallf/tools/robot_factory.py
rallf/tools/runner.py
rallf/tools/selenium_device_factory.py
rallf/tools/task_factory.py
rallf-0.4.5.data/scripts/rallf-py
rallf-0.4.5.dist-info/LICENSE
rallf-0.4.5.dist-info/METADATA
rallf-0.4.5.dist-info/WHEEL
rallf-0.4.5.dist-info/top_level.txt
rallf-0.4.5.dist-info/RECORD
